PythonAirplanePictures.py
pythonairplanepictures-2.0.0.dist-info/LICENSE
pythonairplanepictures-2.0.0.dist-info/METADATA
pythonairplanepictures-2.0.0.dist-info/WHEEL
pythonairplanepictures-2.0.0.dist-info/entry_points.txt
pythonairplanepictures-2.0.0.dist-info/top_level.txt
pythonairplanepictures-2.0.0.dist-info/RECORD
