Metadata-Version: 2.1
Name: pythonairplanepictures
Version: 2.0.0
Summary: A module that gets images from airplane-pictures.net
Author: Glltchyy
License: MIT License
Project-URL: Homepage, https://github.com/Glltchyy/PythonAirplanePictures
Keywords: airplane,airplanes,pictures,downloader
Classifier: Programming Language :: Python
Classifier: Programming Language :: Python :: 3
Requires-Python: >=3.9
License-File: LICENSE
Requires-Dist: requests
